delastic/__init__.py
delastic/apps.py
delastic/indexer.py
delastic/settings.py
delastic/signals.py
delastic/tasks.py
delastic/views.py
delastic/management/__init__.py
delastic/management/commands/__init__.py
delastic/management/commands/create_elastic_index.py
delastic/management/commands/create_elastic_mapping.py
django_elastic-0.0.1.dist-info/DESCRIPTION.rst
django_elastic-0.0.1.dist-info/METADATA
django_elastic-0.0.1.dist-info/RECORD
django_elastic-0.0.1.dist-info/WHEEL
django_elastic-0.0.1.dist-info/metadata.json
django_elastic-0.0.1.dist-info/top_level.txt
example/__init__.py
example/manage.py
example/settings.py
example/urls.py
example/wsgi.py
example/simpleapp/__init__.py
example/simpleapp/admin.py
example/simpleapp/forms.py
example/simpleapp/indexer.py
example/simpleapp/models.py
example/simpleapp/urls.py
example/simpleapp/views.py
example/simpleapp/management/__init__.py
example/simpleapp/management/commands/__init__.py
example/simpleapp/management/commands/get_articles.py
example/simpleapp/migrations/0001_initial.py
example/simpleapp/migrations/__init__.py
