Metadata-Version: 2.0
Name: django-elastic
Version: 0.0.1
Summary: UNKNOWN
Home-page: UNKNOWN
Author: Rangertaha
Author-email: rangertaha@gmail.com
License: UNKNOWN
Platform: UNKNOWN
Classifier: Development Status :: 5 - Production/Stable
Classifier: Environment :: Web Environment
Classifier: Intended Audience :: Developers
Classifier: License :: OSI Approved :: BSD License
Classifier: Operating System :: OS Independent
Classifier: Programming Language :: Python
Classifier: Programming Language :: Python :: 2.7
Classifier: Framework :: Django
Classifier: Framework :: Django :: 1.9
Requires-Dist: Django (>=1.9.7,<2.0.0)
Requires-Dist: elasticsearch (<3.0.0,>=2.0.0)
Requires-Dist: elasticsearch-dsl (<3.0.0,>=2.0.0)
